soccerdata/__init__.py
soccerdata/_common.py
soccerdata/_config.py
soccerdata/clubelo.py
soccerdata/espn.py
soccerdata/fbref.py
soccerdata/fivethirtyeight.py
soccerdata/fotmob.py
soccerdata/match_history.py
soccerdata/sofascore.py
soccerdata/sofifa.py
soccerdata/understat.py
soccerdata/whoscored.py
soccerdata-1.8.6.dist-info/LICENSE.rst
soccerdata-1.8.6.dist-info/METADATA
soccerdata-1.8.6.dist-info/WHEEL
soccerdata-1.8.6.dist-info/RECORD
