Metadata-Version: 2.1
Name: soccerdata
Version: 1.8.6
Summary: A collection of wrappers over soccer data from various websites / APIs.
Home-page: https://github.com/probberechts/soccerdata
License: Apache-2.0
Keywords: soccer,football,soccer data,web scraping,soccer analytics
Author: Pieter Robberechts
Author-email: pieter.robberechts@kuleuven.be
Requires-Python: >=3.9,<3.13
Classifier: License :: OSI Approved :: Apache Software License
Classifier: License :: OSI Approved :: MIT License
Classifier: Operating System :: OS Independent
Classifier: Programming Language :: Python :: 3
Classifier: Programming Language :: Python :: 3.9
Classifier: Programming Language :: Python :: 3.10
Classifier: Programming Language :: Python :: 3.11
Classifier: Programming Language :: Python :: 3.12
Provides-Extra: socceraction
Requires-Dist: PySocks (>=1.7.1,<2.0.0)
Requires-Dist: Unidecode (>=1.2.0,<2.0.0)
Requires-Dist: cloudscraper (>=1.2.71,<2.0.0)
Requires-Dist: html5lib (>=1.1,<2.0)
Requires-Dist: lxml (>=4.9.3,<5.0.0)
Requires-Dist: packaging (>=24.1,<25.0)
Requires-Dist: pandas (>=2.0.0,<3.0.0,!=2.1.0)
Requires-Dist: requests (>=2.23,<3.0)
Requires-Dist: rich (>=13.0.0,<14.0.0)
Requires-Dist: socceraction (>=1.5.3,<2.0.0) ; extra == "socceraction"
Requires-Dist: undetected-chromedriver (>=3.5.0,<4.0.0)
Requires-Dist: unicode (>=2.7,<3.0)
Project-URL: Changelog, https://github.com/probberechts/soccerdata/releases
Project-URL: Documentation, https://soccerdata.readthedocs.io
Project-URL: Repository, https://github.com/probberechts/soccerdata
